rdfreader/__init__.py
rdfreader/chem/__init__.py
rdfreader/chem/mol.py
rdfreader/chem/reaction.py
rdfreader/chem/utils.py
rdfreader/exceptions.py
rdfreader/parse/molblock.py
rdfreader/parse/rxnblock.py
rdfreader/parse/utils.py
rdfreader/rdf.py
rdfreader/write.py
rdfreader-1.0.5.dist-info/METADATA
rdfreader-1.0.5.dist-info/WHEEL
rdfreader-1.0.5.dist-info/licenses/LICENSE.txt
rdfreader-1.0.5.dist-info/RECORD
