Metadata-Version: 2.4
Name: rdfreader
Version: 1.0.5
Summary: Read the full contents of CTAB .rdf files in python. Captures RXN and MOL record using RDKit and reads additional data fields (including solvents/catalysts/agents).
License: MIT
License-File: LICENSE.txt
Keywords: chemistry,rdkit,rdf,rxn,mol,reaction,molecule,reader,parser,chemai,ctab,cheminformatics
Author: ChemAI Ltd.
Author-email: enquiries@chemai.io
Requires-Python: >=3.9,<4.0
Classifier: License :: OSI Approved :: MIT License
Classifier: Programming Language :: Python :: 3
Classifier: Programming Language :: Python :: 3.9
Classifier: Programming Language :: Python :: 3.10
Classifier: Programming Language :: Python :: 3.11
Classifier: Programming Language :: Python :: 3.12
Classifier: Programming Language :: Python :: 3.13
Classifier: Programming Language :: Python :: 3.14
Classifier: Topic :: Scientific/Engineering :: Chemistry
Requires-Dist: rdkit (>=2023.9,<2025.9.3)
Project-URL: Homepage, https://chemai.io
Project-URL: Repository, https://github.com/ChemAILtd/rdfreader/
